pynamics/__init__.py
pynamics/blank_module.py
pynamics/body.py
pynamics/constraint.py
pynamics/dyadic.py
pynamics/force.py
pynamics/frame.py
pynamics/inertia.py
pynamics/integration.py
pynamics/misc_tools.py
pynamics/name_generator.py
pynamics/output.py
pynamics/output_generic.py
pynamics/output_points.py
pynamics/output_points_3d.py
pynamics/particle.py
pynamics/quaternion.py
pynamics/rotation.py
pynamics/signal_approx.py
pynamics/spring.py
pynamics/system.py
pynamics/tanh.py
pynamics/time_series.py
pynamics/tree_node.py
pynamics/variable_types.py
pynamics/vector.py
pynamics_examples/__init__.py
pynamics_examples/babyboot.py
pynamics_examples/ball_rope.py
pynamics_examples/body_in_space.py
pynamics_examples/body_in_space_local.py
pynamics_examples/bouncy2.py
pynamics_examples/bouncy_mod.py
pynamics_examples/cart_pendulum.py
pynamics_examples/cart_pendulum_forced_velocity.py
pynamics_examples/differentiating.py
pynamics_examples/falling_rod.py
pynamics_examples/four_bar.py
pynamics_examples/four_bar2.py
pynamics_examples/fourbar_with_triangles.py
pynamics_examples/fourbar_with_two_triangle.py
pynamics_examples/glider.py
pynamics_examples/motor_load_side.py
pynamics_examples/motor_motor_side.py
pynamics_examples/motorized_pendulum.py
pynamics_examples/parallel_five_bar_jumper.py
pynamics_examples/parallel_five_bar_jumper_foot.py
pynamics_examples/pendulum_2_ways.py
pynamics_examples/pendulum_in_water.py
pynamics_examples/quaternion.py
pynamics_examples/single_dof_bouncer.py
pynamics_examples/springy_pendulum.py
pynamics_examples/standing_stability_test.py
pynamics_examples/triple_pendulum_inverse_dynamics.py
pynamics_examples/triple_pendulum_maximal.py
pynamics_examples/triple_pendulum_rft.py
pynamics_examples/triple_pendulum_swimmer.py
pynamics-0.2.0.dist-info/LICENSE
pynamics-0.2.0.dist-info/METADATA
pynamics-0.2.0.dist-info/WHEEL
pynamics-0.2.0.dist-info/top_level.txt
pynamics-0.2.0.dist-info/RECORD
