Metadata-Version: 2.1
Name: pynamics
Version: 0.2.0
Summary: Pynamics is a package for creating and solving dynamic equations of motion symbolically
Home-page: https://github.com/idealabasu/code_pynamics
Author: Dan Aukes
Author-email: danaukes@danaukes.com
License: MIT
Platform: UNKNOWN
Classifier: Programming Language :: Python
Classifier: Programming Language :: Python :: 3
Requires-Dist: matplotlib
Requires-Dist: numpy
Requires-Dist: scipy
Requires-Dist: sympy
